rdfmodule/__init__.py
rdfmodule/rdf_fixer.py
rdf_fixer-3.1.1.dist-info/LICENSE
rdf_fixer-3.1.1.dist-info/METADATA
rdf_fixer-3.1.1.dist-info/WHEEL
rdf_fixer-3.1.1.dist-info/top_level.txt
rdf_fixer-3.1.1.dist-info/RECORD
