Metadata-Version: 2.1
Name: rdf-fixer
Version: 3.1.1
Summary: Chemical rdf file fixer for exports from Reaxys, SciFinder, Deepmatter, etc.
Home-page: https://github.com/DocMinus/chem-rdf-fixer
Author: Alexander Minidis, DocMinus
Author-email: alexander.minidis@gmail.com
License: MIT
License-File: LICENSE
Requires-Dist: rdkit
Requires-Dist: pandas
Requires-Dist: numpy
